flask_controller/__init__.py
flask_controller/controller.py
flask_controller/register.py
flask_controller/version.py
flask_controller/utils/__init__.py
flask_controller/utils/case_util.py
flask_controller/utils/inspect_util.py
flask_controller-0.0.2.dist-info/METADATA
flask_controller-0.0.2.dist-info/WHEEL
flask_controller-0.0.2.dist-info/top_level.txt
flask_controller-0.0.2.dist-info/zip-safe
flask_controller-0.0.2.dist-info/RECORD
