Metadata-Version: 2.1
Name: flask-controller
Version: 0.0.2
Summary: a extension for flask which can auto register route rule
Home-page: https://github.com/mouday/flask-controller
Author: Peng Shiyu
Author-email: pengshiyuyx@gmail.com
License: MIT
Keywords: flask,controller
Platform: UNKNOWN
Classifier: Programming Language :: Python :: 3
Classifier: Programming Language :: Python :: 3.7
Requires-Dist: case-convert (>=1.1.0)
